pyexplain/__init__.py
pyexplain/functions.py
pyexplain/interact.py
pyexplain/main.py
pyexplain/openai_api.py
pyexplain/prompt.py
pyexplain/utils.py
pyexplain-0.1.0.dist-info/METADATA
pyexplain-0.1.0.dist-info/WHEEL
pyexplain-0.1.0.dist-info/entry_points.txt
pyexplain-0.1.0.dist-info/top_level.txt
pyexplain-0.1.0.dist-info/RECORD
