Metadata-Version: 2.1
Name: pyexplain
Version: 0.1.0
Summary: My first Python library
Author: Me
Classifier: Programming Language :: Python :: 3
Classifier: License :: OSI Approved :: MIT License
Classifier: Operating System :: OS Independent
Requires-Dist: rich
Requires-Dist: colorama
Requires-Dist: openai
Requires-Dist: art
